README.md
setup.cfg
setup.py
twelve_step/__init__.py
twelve_step/arguments.py
twelve_step/constants.py
twelve_step/exclude_packages_factory.py
twelve_step/generate_dependencies.py
twelve_step/main.py
twelve_step/version.txt
twelve_step.egg-info/PKG-INFO
twelve_step.egg-info/SOURCES.txt
twelve_step.egg-info/dependency_links.txt
twelve_step.egg-info/entry_points.txt
twelve_step.egg-info/requires.txt
twelve_step.egg-info/top_level.txt
twelve_step/find_classes/__init__.py
twelve_step/find_classes/find_classes.py
twelve_step/find_imported_classes/__init__.py
twelve_step/find_imported_classes/find_imported_classes_in_imports.py
twelve_step/find_imported_packages/__init__.py
twelve_step/find_imported_packages/find_imported_packages.py
twelve_step/find_imports/__init__.py
twelve_step/find_imports/find_imports_in_file.py
twelve_step/outputs/__init__.py
twelve_step/outputs/console_output.py
twelve_step/outputs/file_output.py
twelve_step/outputs/output_factory.py
twelve_step/outputs/write_dependency_graph.py